{"2P+JRVVWH1nX+JY9RdAKLA==":"1-96x96.png","y0Uzsko31K8eghhx9F1DJw==":"mbr-1387x929.jpg","nwXepoNtaFCiOXM+J48u+w==":"flat1000x1000075f.u1-1000x667.jpg","zVqOj9fo6vwLfWHykIYX8g==":"logotipo-negro-240x120.jpeg","110BOTqfQq1g9JMuRoqJTw==":"descarga-2-240x74.jpg","zYXpRfOSBtSJ3WBe/mmVKg==":"mbr.jpg","tMmFPTsGxHcx3J9RGMhPwg==":"mbr-1.jpg","ZoPxe6iinHvmKEe6MDy7jw==":"screen-shot-2020-09-27-at-9.53.38-p.m..png","99ZtCdisLL3fqtKAULDfOg==":"screen-shot-2020-10-01-at-2.19.36-a.m..png","KlTKr9rEAo+nJxOXtULU7A==":"screen-shot-2020-10-01-at-2.24.06-a.m..png","VOvX2I0UMSy+jILy+ZdSkA==":"screen-shot-2020-10-01-at-2.39.31-a.m..png","IL6HzEusztTQt0FEvdFnRQ==":"screen-shot-2020-10-01-at-2.29.54-a.m..png"}